bulk_sync/__init__.py
tests/__init__.py
tests/models.py
tests/test_settings.py
tests/tests.py
django_bulk_sync-3.3.0.dist-info/LICENSE
django_bulk_sync-3.3.0.dist-info/METADATA
django_bulk_sync-3.3.0.dist-info/WHEEL
django_bulk_sync-3.3.0.dist-info/top_level.txt
django_bulk_sync-3.3.0.dist-info/RECORD
